protobuf/__init__.py
protobuf/douyin.py
douyin_live_fetcher-1.0.0.dist-info/METADATA
douyin_live_fetcher-1.0.0.dist-info/WHEEL
douyin_live_fetcher-1.0.0.dist-info/entry_points.txt
douyin_live_fetcher-1.0.0.dist-info/top_level.txt
douyin_live_fetcher-1.0.0.dist-info/RECORD
