Metadata-Version: 2.1
Name: douyin-live-fetcher
Version: 1.0.0
Summary: Douyin Live Web Fetcher
Author: Original Author
Classifier: Programming Language :: Python :: 3
Classifier: License :: OSI Approved :: MIT License
Classifier: Operating System :: Microsoft :: Windows :: Windows 10
Requires-Python: >=3.7
Requires-Dist: requests==2.31.0
Requires-Dist: betterproto==2.0.0b6
Requires-Dist: websocket-client==1.7.0
Requires-Dist: PyExecJS==1.5.1
Requires-Dist: mini-racer==0.12.4
